librlers.cpython-312-i386-linux-gnu.so
aardwolf/__init__.py
aardwolf/_version.py
aardwolf/channels.py
aardwolf/connection.py
aardwolf/vncconnection.py
aardwolf/commons/__init__.py
aardwolf/commons/cryptolayer.py
aardwolf/commons/factory.py
aardwolf/commons/iosettings.py
aardwolf/commons/params.py
aardwolf/commons/serverinfo.py
aardwolf/commons/target.py
aardwolf/commons/queuedata/__init__.py
aardwolf/commons/queuedata/beep.py
aardwolf/commons/queuedata/clipboard.py
aardwolf/commons/queuedata/constants.py
aardwolf/commons/queuedata/keyboard.py
aardwolf/commons/queuedata/mouse.py
aardwolf/commons/queuedata/video.py
aardwolf/commons/utils/__init__.py
aardwolf/commons/utils/ts2dt.py
aardwolf/develstuff/bitmaptest.py
aardwolf/develstuff/dectest.py
aardwolf/develstuff/pertest.py
aardwolf/develstuff/server_caps
aardwolf/develstuff/srvdata.py
aardwolf/develstuff/transporttest.py
aardwolf/examples/__init__.py
aardwolf/examples/scancommons/__init__.py
aardwolf/examples/scancommons/internal.py
aardwolf/examples/scancommons/targetgens.py
aardwolf/examples/scancommons/utils.py
aardwolf/examples/scanners/__init__.py
aardwolf/examples/scanners/__main__.py
aardwolf/examples/scanners/rdplogin.py
aardwolf/examples/scanners/rdpscaps.py
aardwolf/examples/scanners/rdpscreen.py
aardwolf/extensions/__init__.py
aardwolf/extensions/RDPECLIP/__init__.py
aardwolf/extensions/RDPECLIP/channel.py
aardwolf/extensions/RDPECLIP/clipboard.py
aardwolf/extensions/RDPECLIP/fileprovider.py
aardwolf/extensions/RDPECLIP/protocol/__init__.py
aardwolf/extensions/RDPECLIP/protocol/clienttemporarydirectory.py
aardwolf/extensions/RDPECLIP/protocol/clipboardcapabilities.py
aardwolf/extensions/RDPECLIP/protocol/filecontentsrequest.py
aardwolf/extensions/RDPECLIP/protocol/filecontentsresponse.py
aardwolf/extensions/RDPECLIP/protocol/formatdatarequest.py
aardwolf/extensions/RDPECLIP/protocol/formatdataresponse.py
aardwolf-0.2.13.dist-info/METADATA
aardwolf-0.2.13.dist-info/WHEEL
aardwolf-0.2.13.dist-info/entry_points.txt
aardwolf-0.2.13.dist-info/top_level.txt
aardwolf-0.2.13.dist-info/RECORD
aardwolf-0.2.13.dist-info/licenses/LICENSE
