Metadata-Version: 2.4
Name: aardwolf
Version: 0.2.13
Summary: Asynchronous RDP protocol implementation
Home-page: https://github.com/skelsec/aardwolf
Author: Tamas Jos
Author-email: info@skelsecprojects.com
Classifier: Programming Language :: Python :: 3.8
Classifier: Operating System :: OS Independent
Requires-Python: >=3.9
License-File: LICENSE
Requires-Dist: unicrypto>=0.0.11
Requires-Dist: asyauth>=0.0.16
Requires-Dist: asysocks>=0.2.9
Requires-Dist: tqdm
Requires-Dist: colorama
Requires-Dist: asn1crypto
Requires-Dist: asn1tools
Requires-Dist: pyperclip>=1.8.2
Requires-Dist: arc4>=0.3.0
Requires-Dist: Pillow>=9.0.0
Dynamic: author
Dynamic: author-email
Dynamic: classifier
Dynamic: home-page
Dynamic: license-file
Dynamic: requires-dist
Dynamic: requires-python
Dynamic: summary
